[{"domain":"tenth.bond","status":"available","attractiveness":116,"demand":7,"length":5,"created":"","expires":"","registrar":null,"sectors":"Mathematics"},{"domain":"twentieth.bond","status":"available","attractiveness":92,"demand":3,"length":9,"created":"","expires":"","registrar":null,"sectors":"Mathematics"},{"domain":"nought.bond","status":"available","attractiveness":92,"demand":4,"length":6,"created":"","expires":"","registrar":null,"sectors":"Mathematics"},{"domain":"leash.bond","status":"available","attractiveness":90,"demand":7,"length":5,"created":"","expires":"","registrar":null,"sectors":"General,Health and Fitness,Retail"},{"domain":"sixteen.bond","status":"available","attractiveness":88,"demand":11,"length":7,"created":"","expires":"","registrar":null,"sectors":"Mathematics"},{"domain":"ten.bond","status":"resell","attractiveness":88,"demand":28,"length":3,"created":"2020-11-15T15:37:51.000Z","expires":"2030-11-15T23:59:59.000Z","registrar":"Dominet (HK) Limited","sectors":"General,Mathematics"},{"domain":"cipher.bond","status":"available","attractiveness":86,"demand":29,"length":6,"created":"","expires":"","registrar":null,"sectors":"Mathematics"},{"domain":"xix.bond","status":"available","attractiveness":86,"demand":11,"length":3,"created":"","expires":"","registrar":null,"sectors":"Mathematics"},{"domain":"xiv.bond","status":"available","attractiveness":86,"demand":12,"length":3,"created":"","expires":"","registrar":null,"sectors":"Mathematics"},{"domain":"twentyone.bond","status":"available","attractiveness":84,"demand":13,"length":10,"created":"","expires":"","registrar":null,"sectors":"Mathematics"},{"domain":"nineteen.bond","status":"available","attractiveness":84,"demand":8,"length":8,"created":"","expires":"","registrar":null,"sectors":"Mathematics"},{"domain":"thirteen.bond","status":"available","attractiveness":84,"demand":10,"length":8,"created":"","expires":"","registrar":null,"sectors":"Mathematics"},{"domain":"grand.bond","status":"available","attractiveness":84,"demand":25,"length":5,"created":"","expires":"","registrar":null,"sectors":"Finance,General"},{"domain":"twentytwo.bond","status":"available","attractiveness":84,"demand":11,"length":10,"created":"","expires":"","registrar":null,"sectors":"Mathematics"},{"domain":"decade.bond","status":"available","attractiveness":82,"demand":10,"length":6,"created":"","expires":"","registrar":null,"sectors":"Mathematics"},{"domain":"first.bond","status":"available","attractiveness":80,"demand":36,"length":5,"created":"","expires":"","registrar":null,"sectors":"General,Mathematics"},{"domain":"two.bond","status":"available","attractiveness":80,"demand":24,"length":3,"created":"","expires":"","registrar":null,"sectors":"Mathematics"},{"domain":"twentysix.bond","status":"available","attractiveness":78,"demand":8,"length":10,"created":"","expires":"","registrar":null,"sectors":"Mathematics"},{"domain":"fourteenth.bond","status":"available","attractiveness":76,"demand":1,"length":10,"created":"","expires":"","registrar":null,"sectors":"Mathematics"},{"domain":"threed.bond","status":"available","attractiveness":76,"demand":7,"length":7,"created":"","expires":"","registrar":null,"sectors":"Technology"},{"domain":"thirteenth.bond","status":"available","attractiveness":76,"demand":4,"length":10,"created":"","expires":"","registrar":null,"sectors":"Mathematics"},{"domain":"fifteenth.bond","status":"available","attractiveness":76,"demand":2,"length":9,"created":"","expires":"","registrar":null,"sectors":"Mathematics"},{"domain":"nineteenth.bond","status":"available","attractiveness":76,"demand":3,"length":10,"created":"","expires":"","registrar":null,"sectors":"Mathematics"},{"domain":"hundredth.bond","status":"available","attractiveness":76,"demand":1,"length":9,"created":"","expires":"","registrar":null,"sectors":"Mathematics"},{"domain":"eighteen.bond","status":"available","attractiveness":76,"demand":7,"length":8,"created":"","expires":"","registrar":null,"sectors":"Mathematics"},{"domain":"thousandth.bond","status":"available","attractiveness":76,"demand":1,"length":10,"created":"","expires":"","registrar":null,"sectors":"Mathematics"},{"domain":"trey.bond","status":"available","attractiveness":72,"demand":14,"length":4,"created":"","expires":"","registrar":null,"sectors":"Sports"},{"domain":"trinity.bond","status":"available","attractiveness":72,"demand":18,"length":7,"created":"","expires":"","registrar":null,"sectors":"Religion"},{"domain":"ternary.bond","status":"available","attractiveness":72,"demand":7,"length":7,"created":"","expires":"","registrar":null,"sectors":"Mathematics"},{"domain":"unity.bond","status":"available","attractiveness":70,"demand":40,"length":5,"created":"","expires":"","registrar":null,"sectors":"Mathematics"},{"domain":"threesome.bond","status":"available","attractiveness":68,"demand":5,"length":9,"created":"","expires":"","registrar":null,"sectors":"Entertainment"},{"domain":"thirtieth.bond","status":"available","attractiveness":68,"demand":1,"length":9,"created":"","expires":"","registrar":null,"sectors":"Mathematics"},{"domain":"xxii.bond","status":"available","attractiveness":66,"demand":6,"length":4,"created":"","expires":"","registrar":null,"sectors":"Mathematics"},{"domain":"xvii.bond","status":"available","attractiveness":66,"demand":5,"length":4,"created":"","expires":"","registrar":null,"sectors":"Mathematics"},{"domain":"xiii.bond","status":"available","attractiveness":66,"demand":9,"length":4,"created":"","expires":"","registrar":null,"sectors":"Mathematics"},{"domain":"tenner.bond","status":"available","attractiveness":66,"demand":5,"length":6,"created":"","expires":"","registrar":null,"sectors":"Finance"},{"domain":"thirty.bond","status":"available","attractiveness":66,"demand":8,"length":6,"created":"","expires":"","registrar":null,"sectors":"Mathematics"},{"domain":"deuce.bond","status":"available","attractiveness":66,"demand":9,"length":5,"created":"","expires":"","registrar":null,"sectors":"Sports"},{"domain":"xvi.bond","status":"available","attractiveness":66,"demand":5,"length":3,"created":"","expires":"","registrar":null,"sectors":"Mathematics"},{"domain":"clv.bond","status":"available","attractiveness":66,"demand":10,"length":3,"created":"","expires":"","registrar":null,"sectors":"Mathematics"},{"domain":"onec.bond","status":"available","attractiveness":66,"demand":6,"length":5,"created":"","expires":"","registrar":null,"sectors":"Mathematics"},{"domain":"xii.bond","status":"available","attractiveness":66,"demand":10,"length":3,"created":"","expires":"","registrar":null,"sectors":"Mathematics"},{"domain":"xxi.bond","status":"available","attractiveness":66,"demand":10,"length":3,"created":"","expires":"","registrar":null,"sectors":"Mathematics"},{"domain":"xxvi.bond","status":"available","attractiveness":66,"demand":3,"length":4,"created":"","expires":"","registrar":null,"sectors":"Mathematics"},{"domain":"xviii.bond","status":"available","attractiveness":66,"demand":5,"length":5,"created":"","expires":"","registrar":null,"sectors":"Mathematics"},{"domain":"xxv.bond","status":"available","attractiveness":66,"demand":6,"length":3,"created":"","expires":"","registrar":null,"sectors":"Mathematics"},{"domain":"twodozen.bond","status":"available","attractiveness":62,"demand":1,"length":9,"created":"","expires":"","registrar":null,"sectors":"Mathematics"},{"domain":"longdozen.bond","status":"available","attractiveness":62,"demand":2,"length":10,"created":"","expires":"","registrar":null,"sectors":"Mathematics"},{"domain":"troika.bond","status":"available","attractiveness":62,"demand":8,"length":6,"created":"","expires":"","registrar":null,"sectors":"Politics"},{"domain":"eighteenth.bond","status":"available","attractiveness":62,"demand":1,"length":10,"created":"","expires":"","registrar":null,"sectors":"Mathematics"},{"domain":"eleventh.bond","status":"available","attractiveness":62,"demand":5,"length":8,"created":"","expires":"","registrar":null,"sectors":"Mathematics"},{"domain":"chiliad.bond","status":"available","attractiveness":62,"demand":2,"length":7,"created":"","expires":"","registrar":null,"sectors":"Mathematics"},{"domain":"sixteenth.bond","status":"available","attractiveness":62,"demand":1,"length":9,"created":"","expires":"","registrar":null,"sectors":"Mathematics"},{"domain":"clxx.bond","status":"available","attractiveness":60,"demand":3,"length":4,"created":"","expires":"","registrar":null,"sectors":"Mathematics"},{"domain":"clxxx.bond","status":"available","attractiveness":60,"demand":1,"length":5,"created":"","expires":"","registrar":null,"sectors":"Mathematics"},{"domain":"cxxxv.bond","status":"available","attractiveness":60,"demand":2,"length":5,"created":"","expires":"","registrar":null,"sectors":"Mathematics"},{"domain":"cxlv.bond","status":"available","attractiveness":60,"demand":2,"length":4,"created":"","expires":"","registrar":null,"sectors":"Mathematics"},{"domain":"clxv.bond","status":"available","attractiveness":60,"demand":1,"length":4,"created":"","expires":"","registrar":null,"sectors":"Mathematics"},{"domain":"xcl.bond","status":"available","attractiveness":60,"demand":5,"length":3,"created":"","expires":"","registrar":null,"sectors":"Mathematics"},{"domain":"cxxx.bond","status":"available","attractiveness":60,"demand":4,"length":4,"created":"","expires":"","registrar":null,"sectors":"Mathematics"},{"domain":"cxxv.bond","status":"available","attractiveness":60,"demand":1,"length":4,"created":"","expires":"","registrar":null,"sectors":"Mathematics"},{"domain":"clxxv.bond","status":"available","attractiveness":60,"demand":1,"length":5,"created":"","expires":"","registrar":null,"sectors":"Mathematics"},{"domain":"clx.bond","status":"available","attractiveness":60,"demand":10,"length":3,"created":"","expires":"","registrar":null,"sectors":"Mathematics"},{"domain":"cxx.bond","status":"available","attractiveness":60,"demand":10,"length":3,"created":"","expires":"","registrar":null,"sectors":"Mathematics"},{"domain":"cxl.bond","status":"available","attractiveness":60,"demand":7,"length":3,"created":"","expires":"","registrar":null,"sectors":"Mathematics"},{"domain":"twelfth.bond","status":"available","attractiveness":58,"demand":2,"length":7,"created":"","expires":"","registrar":null,"sectors":"Mathematics"},{"domain":"centesimal.bond","status":"available","attractiveness":58,"demand":1,"length":10,"created":"","expires":"","registrar":null,"sectors":"Mathematics"},{"domain":"xxvii.bond","status":"available","attractiveness":56,"demand":3,"length":5,"created":"","expires":"","registrar":null,"sectors":"Mathematics"},{"domain":"xxiii.bond","status":"available","attractiveness":56,"demand":5,"length":5,"created":"","expires":"","registrar":null,"sectors":"Mathematics"},{"domain":"thirtytwo.bond","status":"available","attractiveness":56,"demand":5,"length":10,"created":"","expires":"","registrar":null,"sectors":"Mathematics"},{"domain":"xxviii.bond","status":"available","attractiveness":56,"demand":1,"length":6,"created":"","expires":"","registrar":null,"sectors":"Mathematics"},{"domain":"xxix.bond","status":"available","attractiveness":56,"demand":4,"length":4,"created":"","expires":"","registrar":null,"sectors":"Mathematics"},{"domain":"xxiv.bond","status":"available","attractiveness":56,"demand":5,"length":4,"created":"","expires":"","registrar":null,"sectors":"Mathematics"},{"domain":"xxxi.bond","status":"available","attractiveness":56,"demand":9,"length":4,"created":"","expires":"","registrar":null,"sectors":"Mathematics"},{"domain":"thirtyone.bond","status":"available","attractiveness":56,"demand":5,"length":10,"created":"","expires":"","registrar":null,"sectors":"Mathematics"},{"domain":"deuceace.bond","status":"available","attractiveness":54,"demand":2,"length":9,"created":"","expires":"","registrar":null,"sectors":"Sports"},{"domain":"triplet.bond","status":"available","attractiveness":50,"demand":8,"length":7,"created":"","expires":"","registrar":null,"sectors":"Science"}]